{
  "data": {
    "article": {},
    "attachments": {},
    "author_id": "2029908828125548546",
    "conversation_id": "2040788400949862499",
    "created_at": "2026-04-05T14:45:24.000Z",
    "edit_controls": {
      "editable_until": "2026-04-05T15:45:24.000Z",
      "edits_remaining": 5,
      "is_edit_eligible": false
    },
    "edit_history_tweet_ids": [
      "2040802992308572354"
    ],
    "entities": {
      "mentions": [
        {
          "end": 15,
          "id": "1810873766119100416",
          "start": 0,
          "username": "RainBuild_2024"
        }
      ]
    },
    "geo": {},
    "id": "2040802992308572354",
    "in_reply_to_user_id": "1810873766119100416",
    "lang": "zh",
    "note_tweet": {
      "entities": {}
    },
    "possibly_sensitive": false,
    "public_metrics": {
      "bookmark_count": 0,
      "impression_count": 0,
      "like_count": 0,
      "quote_count": 0,
      "reply_count": 0,
      "retweet_count": 0
    },
    "referenced_tweets": [
      {
        "id": "2040788400949862499",
        "type": "replied_to"
      }
    ],
    "reply_settings": "everyone",
    "text": "@RainBuild_2024 老唐总能整出一些我闻所未闻的活"
  },
  "includes": {
    "tweets": [
      {
        "article": {},
        "attachments": {},
        "author_id": "2029908828125548546",
        "conversation_id": "2040788400949862499",
        "created_at": "2026-04-05T14:45:24.000Z",
        "edit_controls": {
          "editable_until": "2026-04-05T15:45:24.000Z",
          "edits_remaining": 5,
          "is_edit_eligible": false
        },
        "edit_history_tweet_ids": [
          "2040802992308572354"
        ],
        "entities": {
          "mentions": [
            {
              "end": 15,
              "id": "1810873766119100416",
              "start": 0,
              "username": "RainBuild_2024"
            }
          ]
        },
        "geo": {},
        "id": "2040802992308572354",
        "in_reply_to_user_id": "1810873766119100416",
        "lang": "zh",
        "note_tweet": {
          "entities": {}
        },
        "possibly_sensitive": false,
        "public_metrics": {
          "bookmark_count": 0,
          "impression_count": 0,
          "like_count": 0,
          "quote_count": 0,
          "reply_count": 0,
          "retweet_count": 0
        },
        "referenced_tweets": [
          {
            "id": "2040788400949862499",
            "type": "replied_to"
          }
        ],
        "reply_settings": "everyone",
        "text": "@RainBuild_2024 老唐总能整出一些我闻所未闻的活"
      },
      {
        "article": {},
        "attachments": {},
        "author_id": "1810873766119100416",
        "conversation_id": "2040788400949862499",
        "created_at": "2026-04-05T13:47:25.000Z",
        "edit_controls": {
          "editable_until": "2026-04-05T14:47:25.000Z",
          "edits_remaining": 5,
          "is_edit_eligible": true
        },
        "edit_history_tweet_ids": [
          "2040788400949862499"
        ],
        "entities": {
          "urls": [
            {
              "display_url": "x.com/xynmtfxyn/stat…",
              "end": 41,
              "expanded_url": "https://twitter.com/xynmtfxyn/status/2040754971604369865",
              "start": 18,
              "url": "https://t.co/vai8wdFrFE"
            }
          ]
        },
        "geo": {},
        "id": "2040788400949862499",
        "lang": "zh",
        "note_tweet": {
          "entities": {}
        },
        "possibly_sensitive": false,
        "public_metrics": {
          "bookmark_count": 0,
          "impression_count": 690,
          "like_count": 18,
          "quote_count": 0,
          "reply_count": 8,
          "retweet_count": 0
        },
        "referenced_tweets": [
          {
            "id": "2040754971604369865",
            "type": "quoted"
          }
        ],
        "reply_settings": "everyone",
        "text": "这他妈是tyw小号？这扯不扯啊啊啊 https://t.co/vai8wdFrFE"
      }
    ],
    "users": [
      {
        "created_at": "2026-03-06T13:16:07.000Z",
        "description": "一只od的经验猫，憧憬成为od届的大手子。",
        "id": "2029908828125548546",
        "location": "普瑞巴林行动小组",
        "name": "EXPcat",
        "pinned_tweet_id": "2037056043453432137",
        "profile_image_url": "https://pbs.twimg.com/profile_images/2040793488061861888/h0unB2hS_normal.jpg",
        "protected": false,
        "public_metrics": {
          "followers_count": 196,
          "following_count": 162,
          "like_count": 106,
          "listed_count": 0,
          "media_count": 21,
          "tweet_count": 417
        },
        "username": "bui_tu46916",
        "verified": false
      },
      {
        "created_at": "2024-07-10T03:08:51.000Z",
        "description": "RainEngine联合创始人/Android ROM开发/产品项目运营/喜欢摄影/喜欢折腾各类的Android手机/偶尔发些日常/PM前请征得同意否则Ban/GMT+8/上一个账号@RainEngine2024",
        "entities": {
          "description": {
            "mentions": [
              {
                "end": 106,
                "start": 91,
                "username": "RainEngine2024"
              }
            ]
          }
        },
        "id": "1810873766119100416",
        "name": "晴日向",
        "pinned_tweet_id": "2036689318245531849",
        "profile_image_url": "https://pbs.twimg.com/profile_images/2035649404812853248/cnSm6sUs_normal.jpg",
        "protected": false,
        "public_metrics": {
          "followers_count": 9402,
          "following_count": 889,
          "like_count": 70110,
          "listed_count": 17,
          "media_count": 1439,
          "tweet_count": 10126
        },
        "username": "RainBuild_2024",
        "verified": true
      }
    ]
  }
}