{
  "data": {
    "article": {},
    "attachments": {},
    "author_id": "2029908828125548546",
    "conversation_id": "2030357715277738092",
    "created_at": "2026-03-07T19:02:12.000Z",
    "edit_controls": {
      "editable_until": "2026-03-07T20:02:12.000Z",
      "edits_remaining": 5,
      "is_edit_eligible": false
    },
    "edit_history_tweet_ids": [
      "2030358370998419814"
    ],
    "entities": {
      "mentions": [
        {
          "end": 13,
          "id": "1556279645502427136",
          "start": 0,
          "username": "tianxiao0502"
        }
      ]
    },
    "geo": {},
    "id": "2030358370998419814",
    "in_reply_to_user_id": "1556279645502427136",
    "lang": "zh",
    "note_tweet": {
      "entities": {}
    },
    "possibly_sensitive": false,
    "public_metrics": {
      "bookmark_count": 0,
      "impression_count": 0,
      "like_count": 0,
      "quote_count": 0,
      "reply_count": 0,
      "retweet_count": 0
    },
    "referenced_tweets": [
      {
        "id": "2030357715277738092",
        "type": "replied_to"
      }
    ],
    "reply_settings": "everyone",
    "text": "@tianxiao0502 会怎么样"
  },
  "includes": {
    "tweets": [
      {
        "article": {},
        "attachments": {},
        "author_id": "2029908828125548546",
        "conversation_id": "2030357715277738092",
        "created_at": "2026-03-07T19:02:12.000Z",
        "edit_controls": {
          "editable_until": "2026-03-07T20:02:12.000Z",
          "edits_remaining": 5,
          "is_edit_eligible": false
        },
        "edit_history_tweet_ids": [
          "2030358370998419814"
        ],
        "entities": {
          "mentions": [
            {
              "end": 13,
              "id": "1556279645502427136",
              "start": 0,
              "username": "tianxiao0502"
            }
          ]
        },
        "geo": {},
        "id": "2030358370998419814",
        "in_reply_to_user_id": "1556279645502427136",
        "lang": "zh",
        "note_tweet": {
          "entities": {}
        },
        "possibly_sensitive": false,
        "public_metrics": {
          "bookmark_count": 0,
          "impression_count": 0,
          "like_count": 0,
          "quote_count": 0,
          "reply_count": 0,
          "retweet_count": 0
        },
        "referenced_tweets": [
          {
            "id": "2030357715277738092",
            "type": "replied_to"
          }
        ],
        "reply_settings": "everyone",
        "text": "@tianxiao0502 会怎么样"
      },
      {
        "article": {},
        "attachments": {},
        "author_id": "1556279645502427136",
        "conversation_id": "2030357715277738092",
        "created_at": "2026-03-07T18:59:36.000Z",
        "edit_controls": {
          "editable_until": "2026-03-07T19:59:36.000Z",
          "edits_remaining": 5,
          "is_edit_eligible": true
        },
        "edit_history_tweet_ids": [
          "2030357715277738092"
        ],
        "entities": {},
        "geo": {},
        "id": "2030357715277738092",
        "lang": "zh",
        "note_tweet": {
          "entities": {}
        },
        "possibly_sensitive": false,
        "public_metrics": {
          "bookmark_count": 0,
          "impression_count": 2,
          "like_count": 0,
          "quote_count": 0,
          "reply_count": 1,
          "retweet_count": 0
        },
        "reply_settings": "everyone",
        "text": "给嗑阿片的一个建议：别去吃自助。口服阿片类药物后肠道阿片受体也会被激动的，半天蠕动一次，都这样了还往肚子里硬塞东西？！"
      }
    ],
    "users": [
      {
        "created_at": "2026-03-06T13:16:07.000Z",
        "description": "一只od的经验猫",
        "id": "2029908828125548546",
        "location": "普瑞巴林行动小组",
        "name": "EXPcat",
        "profile_image_url": "https://pbs.twimg.com/profile_images/2029921107885838338/S82ZZ0Mv_normal.jpg",
        "protected": false,
        "public_metrics": {
          "followers_count": 7,
          "following_count": 28,
          "like_count": 3,
          "listed_count": 0,
          "media_count": 1,
          "tweet_count": 21
        },
        "username": "bui_tu46916",
        "verified": false
      },
      {
        "created_at": "2022-08-07T14:02:46.000Z",
        "description": "PsydrugsWiki编辑│可以叫我天晓",
        "entities": {
          "url": {
            "urls": [
              {
                "display_url": "psydrugs.org",
                "end": 23,
                "expanded_url": "http://psydrugs.org",
                "start": 0,
                "url": "https://t.co/kbttTgmTXj"
              }
            ]
          }
        },
        "id": "1556279645502427136",
        "location": "東京 新宿区 药物研究所",
        "name": "Pr5ga6al1N",
        "pinned_tweet_id": "2015445624033051032",
        "profile_image_url": "https://pbs.twimg.com/profile_images/2014370395449942016/DvJfSMoR_normal.jpg",
        "protected": false,
        "public_metrics": {
          "followers_count": 220,
          "following_count": 145,
          "like_count": 559,
          "listed_count": 0,
          "media_count": 40,
          "tweet_count": 499
        },
        "url": "https://t.co/kbttTgmTXj",
        "username": "tianxiao0502",
        "verified": false
      }
    ]
  }
}