{
  "data": {
    "article": {},
    "attachments": {
      "media_keys": [
        "3_2033909649725173762"
      ]
    },
    "author_id": "2029908828125548546",
    "conversation_id": "2033900894748848144",
    "created_at": "2026-03-17T14:13:43.000Z",
    "edit_controls": {
      "editable_until": "2026-03-17T15:13:43.000Z",
      "edits_remaining": 5,
      "is_edit_eligible": false
    },
    "edit_history_tweet_ids": [
      "2033909652325601412"
    ],
    "entities": {
      "mentions": [
        {
          "end": 13,
          "id": "1567203042872926208",
          "start": 0,
          "username": "Akinoyo_desu"
        },
        {
          "end": 28,
          "id": "1837114188046684161",
          "start": 14,
          "username": "winterfruit_1"
        }
      ],
      "urls": [
        {
          "display_url": "pic.x.com/pTT8Tp6d3i",
          "end": 52,
          "expanded_url": "https://x.com/bui_tu46916/status/2033909652325601412/photo/1",
          "media_key": "3_2033909649725173762",
          "start": 29,
          "url": "https://t.co/pTT8Tp6d3i"
        }
      ]
    },
    "geo": {},
    "id": "2033909652325601412",
    "in_reply_to_user_id": "1567203042872926208",
    "lang": "qme",
    "note_tweet": {
      "entities": {}
    },
    "possibly_sensitive": false,
    "public_metrics": {
      "bookmark_count": 0,
      "impression_count": 0,
      "like_count": 0,
      "quote_count": 0,
      "reply_count": 0,
      "retweet_count": 0
    },
    "referenced_tweets": [
      {
        "id": "2033908488381075952",
        "type": "replied_to"
      }
    ],
    "reply_settings": "everyone",
    "text": "@Akinoyo_desu @winterfruit_1 https://t.co/pTT8Tp6d3i"
  },
  "includes": {
    "media": [
      {
        "height": 582,
        "media_key": "3_2033909649725173762",
        "public_metrics": {},
        "type": "photo",
        "url": "https://pbs.twimg.com/media/HDnmDOEbsAIQZg9.jpg",
        "width": 798
      }
    ],
    "tweets": [
      {
        "article": {},
        "attachments": {
          "media_keys": [
            "3_2033909649725173762"
          ]
        },
        "author_id": "2029908828125548546",
        "conversation_id": "2033900894748848144",
        "created_at": "2026-03-17T14:13:43.000Z",
        "edit_controls": {
          "editable_until": "2026-03-17T15:13:43.000Z",
          "edits_remaining": 5,
          "is_edit_eligible": false
        },
        "edit_history_tweet_ids": [
          "2033909652325601412"
        ],
        "entities": {
          "mentions": [
            {
              "end": 13,
              "id": "1567203042872926208",
              "start": 0,
              "username": "Akinoyo_desu"
            },
            {
              "end": 28,
              "id": "1837114188046684161",
              "start": 14,
              "username": "winterfruit_1"
            }
          ],
          "urls": [
            {
              "display_url": "pic.x.com/pTT8Tp6d3i",
              "end": 52,
              "expanded_url": "https://x.com/bui_tu46916/status/2033909652325601412/photo/1",
              "media_key": "3_2033909649725173762",
              "start": 29,
              "url": "https://t.co/pTT8Tp6d3i"
            }
          ]
        },
        "geo": {},
        "id": "2033909652325601412",
        "in_reply_to_user_id": "1567203042872926208",
        "lang": "qme",
        "note_tweet": {
          "entities": {}
        },
        "possibly_sensitive": false,
        "public_metrics": {
          "bookmark_count": 0,
          "impression_count": 0,
          "like_count": 0,
          "quote_count": 0,
          "reply_count": 0,
          "retweet_count": 0
        },
        "referenced_tweets": [
          {
            "id": "2033908488381075952",
            "type": "replied_to"
          }
        ],
        "reply_settings": "everyone",
        "text": "@Akinoyo_desu @winterfruit_1 https://t.co/pTT8Tp6d3i"
      },
      {
        "article": {},
        "attachments": {},
        "author_id": "1567203042872926208",
        "conversation_id": "2033900894748848144",
        "created_at": "2026-03-17T14:09:06.000Z",
        "edit_controls": {
          "editable_until": "2026-03-17T15:09:06.000Z",
          "edits_remaining": 5,
          "is_edit_eligible": false
        },
        "edit_history_tweet_ids": [
          "2033908488381075952"
        ],
        "entities": {
          "mentions": [
            {
              "end": 12,
              "id": "2029908828125548546",
              "start": 0,
              "username": "bui_tu46916"
            },
            {
              "end": 27,
              "id": "1837114188046684161",
              "start": 13,
              "username": "winterfruit_1"
            }
          ]
        },
        "geo": {},
        "id": "2033908488381075952",
        "in_reply_to_user_id": "2029908828125548546",
        "lang": "ja",
        "note_tweet": {
          "entities": {}
        },
        "possibly_sensitive": false,
        "public_metrics": {
          "bookmark_count": 0,
          "impression_count": 2,
          "like_count": 0,
          "quote_count": 0,
          "reply_count": 1,
          "retweet_count": 0
        },
        "referenced_tweets": [
          {
            "id": "2033907678947512358",
            "type": "replied_to"
          }
        ],
        "reply_settings": "everyone",
        "text": "@bui_tu46916 @winterfruit_1 四川男同来了"
      }
    ],
    "users": [
      {
        "created_at": "2026-03-06T13:16:07.000Z",
        "description": "一只od的经验猫，憧憬成为od届的大手子。",
        "id": "2029908828125548546",
        "location": "普瑞巴林行动小组",
        "name": "EXPcat",
        "pinned_tweet_id": "2030828686929453530",
        "profile_image_url": "https://pbs.twimg.com/profile_images/2029921107885838338/S82ZZ0Mv_normal.jpg",
        "protected": false,
        "public_metrics": {
          "followers_count": 71,
          "following_count": 84,
          "like_count": 22,
          "listed_count": 0,
          "media_count": 6,
          "tweet_count": 131
        },
        "username": "bui_tu46916",
        "verified": false
      },
      {
        "created_at": "2022-09-06T17:28:25.000Z",
        "description": "别说完蛋这种话！/ \n旧名义：仿生喹硫平/\n梨❤️@Eternal1uv9/\n涘🧊@winterfruit_1 /\n渡 🚣‍♂️@noth1nghere14/\n♠️🅰️@w0sh1Asak1 /\n聖 🍜@shungleemain /\n提问：https://t.co/IopkqyzpO2",
        "entities": {
          "description": {
            "mentions": [
              {
                "end": 37,
                "start": 25,
                "username": "Eternal1uv9"
              },
              {
                "end": 55,
                "start": 41,
                "username": "winterfruit_1"
              },
              {
                "end": 78,
                "start": 64,
                "username": "noth1nghere14"
              },
              {
                "end": 95,
                "start": 84,
                "username": "w0sh1Asak1"
              },
              {
                "end": 114,
                "start": 101,
                "username": "shungleemain"
              }
            ],
            "urls": [
              {
                "display_url": "ngl.link/akinoyo",
                "end": 143,
                "expanded_url": "https://ngl.link/akinoyo",
                "start": 120,
                "url": "https://t.co/IopkqyzpO2"
              }
            ]
          },
          "url": {
            "urls": [
              {
                "display_url": "psydrugs.org",
                "end": 23,
                "expanded_url": "http://psydrugs.org",
                "start": 0,
                "url": "https://t.co/bYHkyXl80J"
              }
            ]
          }
        },
        "id": "1567203042872926208",
        "location": "偉大的天國",
        "name": "Akino5150#海山二",
        "pinned_tweet_id": "1992482113288057078",
        "profile_image_url": "https://pbs.twimg.com/profile_images/2011689303659986945/O3P_h217_normal.jpg",
        "protected": false,
        "public_metrics": {
          "followers_count": 808,
          "following_count": 823,
          "like_count": 3432,
          "listed_count": 1,
          "media_count": 101,
          "tweet_count": 1052
        },
        "url": "https://t.co/bYHkyXl80J",
        "username": "Akinoyo_desu",
        "verified": true
      },
      {
        "created_at": "2024-09-20T12:59:07.000Z",
        "description": "💙💙💙 / Love @w0sh1Asak1 / WinterFruit /  💙💙💙🔮里账：@_Yuyuko_FTZ 🔮",
        "entities": {
          "description": {
            "mentions": [
              {
                "end": 22,
                "start": 11,
                "username": "w0sh1Asak1"
              },
              {
                "end": 59,
                "start": 47,
                "username": "_Yuyuko_FTZ"
              }
            ]
          }
        },
        "id": "1837114188046684161",
        "location": "下一个将死未死的夏季",
        "name": "Winit420 #天苑四",
        "pinned_tweet_id": "2033561989923103038",
        "profile_image_url": "https://pbs.twimg.com/profile_images/2011293938624446464/pWX68IiR_normal.jpg",
        "protected": false,
        "public_metrics": {
          "followers_count": 2419,
          "following_count": 1453,
          "like_count": 36797,
          "listed_count": 7,
          "media_count": 1521,
          "tweet_count": 10831
        },
        "username": "winterfruit_1",
        "verified": false
      }
    ]
  }
}